{"last_tab":"0","favicon":{"url":"","id":"","height":"","width":"","thumbnail":""},"logo":{"url":"http://artbees.net/themes/ken-demo/shopper/wp-content/uploads/sites/9/2014/12/main-logo.png","id":"22","height":"44","width":"128","thumbnail":"http://artbees.net/themes/ken-demo/shopper/wp-content/uploads/sites/9/2014/12/main-logo.png"},"logo-retina":{"url":"","id":"","height":"","width":"","thumbnail":""},"logo-light":{"url":"","id":"","height":"","width":"","thumbnail":""},"logo-light-retina":{"url":"","id":"","height":"","width":"","thumbnail":""},"preloader-logo":{"url":"","id":"","height":"","width":"","thumbnail":""},"mobile-logo":{"url":"","id":"","height":"","width":"","thumbnail":""},"mobile-logo-retina":{"url":"","id":"","height":"","width":"","thumbnail":""},"res-nav-width":"1140","grid-width":"1140","content-width":"70","side-dashboard":"1","side-dashboard-icon":"","breadcrumb":"1","smooth-scroll":"1","pages-comments":"0","custom-sidebar":["Shop 1","Shop 2","Shop 3","Shop 4","product loop 1","product loop 2","Shoes Mega Menu 1","Shoes Mega Menu 2","Shoes Mega Menu 3","Shoes Mega Menu 4","shop 5","Bags Mega Menu 1"],"typekit-id":"","disable-quick-contact":"0","skin-quick-contact":"0","header-structure":"standard","header-location":"top","vertical-header-state":"expanded","header-vertical-width":"280","header-padding":"80","header-padding-vertical":"30","header-align":"center","nav-alignment":"left","boxed-header":"1","sticky-header":"1","squeeze-sticky-header":"1","header-border-top":"0","header-search":"1","header-search-location":"left","header-wpml":"2","page-title-pages":"1","loggedin_menu":"primary-menu","header-social-select":"header_toolbar","header-toolbar":"1","header-toolbar-phone":"CALL US: 1-800-328439 (MY KEN)","header-toolbar-phone-icon":"mk-icon-phone","header-toolbar-email":"45 Park Avenue, Apt. 303. New York, NY 10016","header-toolbar-email-icon":"mk-icon-phone","toolbar-custom-menu":"38","header-social-facebook":"#","header-social-twitter":"","header-social-rss":"","header-social-dribbble":"#","header-social-pinterest":"#","header-social-instagram":"","header-social-google-plus":"","header-social-linkedin":"","header-social-youtube":"","header-social-vimeo":"","header-social-spotify":"","header-social-tumblr":"","header-social-behance":"","header-social-WhatsApp":"","header-social-qzone":"","header-social-vkcom":"","header-social-imdb":"","header-social-renren":"","header-social-weibo":"","footer":"1","footer-layout":"sub_third_third","sub-footer":"1","footer-copyright":"© 2015 Artbees Shop Template Made By The Ken WordPress Theme","subfooter-logos-src":{"url":"http://artbees.net/themes/ken-demo/shopper/wp-content/uploads/sites/9/2015/01/paypal_cart_logos.png","id":"24115","height":"29","width":"301","thumbnail":"http://artbees.net/themes/ken-demo/shopper/wp-content/uploads/sites/9/2015/01/paypal_cart_logos-150x29.png"},"subfooter-logos-link":"#","social-facebook":"","social-twitter":"","social-rss":"","social-dribbble":"","social-pinterest":"","social-instagram":"","social-google-plus":"","social-linkedin":"","social-youtube":"","social-vimeo":"","social-spotify":"","social-tumblr":"","social-behance":"","social-whatsapp":"","social-wechat":"","social-qzone":"","social-vkcom":"","social-imdb":"","social-renren":"","social-weibo":"","body-font":{"font-family":"Merriweather","font-options":"","google":"1","font-backup":"","font-weight":"700","font-style":"","subsets":"","font-size":"13px"},"heading-font":{"font-family":"","font-options":"","google":"1","font-weight":"","font-style":"","subsets":""},"widget-title":{"font-family":"Merriweather","font-options":"","google":"1","font-weight":"400","font-style":"","font-size":"13px"},"page-title-size":"18","p-text-size":"13","p-line-height":"26","main-nav-font":{"font-family":"Merriweather","font-options":"","google":"1","font-weight":"700","font-style":"","font-size":"15px"},"main-nav-item-space":"25","vertical-nav-item-space":"10","main-nav-top-transform":"uppercase","sub-nav-top-size":"12","sub-nav-top-transform":"uppercase","sub-nav-top-weight":"normal","toolbar-font":{"font-family":"Montserrat","font-options":"","google":"1","font-weight":"400","font-style":"","font-size":"10px"},"typekit-font-family":"","typekit-element-names":"","accent-color":"#d3b76c","hover-overlay-color":"#d3b76c","body-txt-color":"#696969","heading-color":"#393836","link-color":{"regular":"#333333","hover":"#d3b76c","active":""},"page-title-color":"#ffffff","dashboard-title-color":"#959595","dashboard-txt-color":"#6f6f6f","dashboard-link-color":{"regular":"#afafaf","hover":"#d3b76c","active":""},"sidebar-title-color":"#555555","sidebar-txt-color":"#666666","sidebar-link-color":{"regular":"#444444","hover":"#d3b76c","active":""},"footer-title-color":"#959595","footer-txt-color":"#6f6f6f","footer-link-color":{"regular":"#666666","hover":"#d3b76c","active":""},"sub-footer-border-top":"1","footer-social-color":{"regular":"#666666","hover":"#d3b76c","active":""},"footer-socket-color":"#666666","widget-title-divider":"1","main-nav-top-color":{"regular":"#666666","hover":"#d3b76c","bg":"","bg-hover":""},"main-nav-sub-bg":"#fafafa","main-nav-sub-color":{"regular":"#444444","hover":"#000000","bg":"","bg-hover":"#d3b76c"},"navigation-border-top":"1","toolbar-border-top":"1","toolbar-border-bottom-color":"","toolbar-text-color":"","toolbar-phone-email-icon-color":"#444444","toolbar-link-color":{"regular":"#444444","hover":"#d3b76c"},"toolbar-social-link-color":{"regular":"#444444","hover":"#d3b76c"},"header-search-icon-color":"","preloader-txt-color":"#444444","preloader-bg-color":"#ffffff","preloader-bar-color":"","breadcrumb-skin":"light","breadcrumb-skin-custom":{"regular":"#ffffff","hover":"#000000"},"custom-css":"                                            ","custom-js":"                        jQuery(document).ready(function(){\r\n\r\n});                    ","body-layout":"full","body-bg":{"url":"","id":"","color":"#ffffff","position":"right bottom","attachment":"scroll","repeat":"repeat","cover":"0"},"header-bg":{"url":"","id":"","color":"#ffffff","position":"right bottom","attachment":"scroll","repeat":"repeat","cover":"0"},"header-bottom-border":"","toolbar-bg":{"url":"","id":"","color":"#eeeeee","position":"right bottom","attachment":"scroll","repeat":"repeat","cover":"0"},"page-title-bg":{"url":"","id":"","color":"#d3b76c","position":"right bottom","attachment":"scroll","repeat":"repeat","cover":"0","border":"#d3b76c"},"page-bg":{"url":"","id":"","color":"#ffffff","position":"right bottom","attachment":"scroll","repeat":"repeat","cover":"0"},"footer-bg":{"url":"","id":"","color":"#eeeeee","position":"right bottom","attachment":"scroll","repeat":"repeat","cover":"0"},"sub-footer-bg":"#141414","dashboard-bg":"#191919","page-title-blog":"1","blog_next_prev":"1","blog-featured-image":"1","blog-image-crop":"1","blog-single-image-height":"350","blog-single-related-posts":"1","blog-single-about-author":"1","blog-single-social-share":"1","blog-single-comments":"1","archive-layout":"right","archive-loop-style":"classic","archive-page-title":"1","page-title-portfolio":"1","portfolio-slug":"portfolio-posts","portfolio_next_prev":"1","portfolio-single-image":"1","portfolio-image-crop":"1","Portfolio-single-image-height":"350","portfolio-single-related":"1","portfolio-single-comments":"0","portfolio-archive-loop-style":"","woo-shop-layout":"right","woo-loop-thumb-height":"330","woo_loop_image_size":"crop","woo-single-thumb-height":"800","woo_single_image_size":"crop","woo-single-layout":"right","checkout-box":"1","woo-image-quality":"1","woo-single-title":"1","woo-single-show-title":"1","woo-shop-loop-title":"1","twitter-consumer-key":"","twitter-consumer-secret":"","twitter-access-token":"","twitter-access-token-secret":"","flickr-api-key":"78aa6852d4fee57154ff181d7b18cee4","google-analytics":"","minify-js":"1","minify-css":"1","remove-js-css-ver":"1","typekit-info":"","opt-import-export":"","redux-backup":1}